sankalp/__init__.py
sankalp/cli_controllers/__init__.py
sankalp/cli_controllers/focus_controller.py
sankalp/cli_controllers/reminder_controller.py
sankalp/cli_controllers/task_controller.py
sankalp/cli_controllers/task_session_controller.py
sankalp/db_connecter/__init__.py
sankalp/db_connecter/base_model.py
sankalp/logs/scheduler.err
sankalp/logs/scheduler.log
sankalp/logs/scheduler.out
sankalp/main.py
sankalp/migrate.py
sankalp/migrations/001_migration_00001.py
sankalp/migrations/002_migration_00002.py
sankalp/migrations/003_migration_00003.py
sankalp/migrations/004_migration_00004.py
sankalp/models/__init__.py
sankalp/models/focus.py
sankalp/models/priority.py
sankalp/models/reminder.py
sankalp/models/status.py
sankalp/models/task.py
sankalp/models/task_session.py
sankalp/reminder_policy.json
sankalp/requirements.txt
sankalp/scheduler.sh
sankalp/scheduler_manager.py
sankalp/scheduler_service/reminder_scheduler.py
sankalp/services/__init__.py
sankalp/services/focus_service.py
sankalp/services/reminder_service.py
sankalp/services/task_session_service.py
sankalp/services/tasks_service.py
sankalp/utils/__init__.py
sankalp/utils/cache_utils.py
sankalp/utils/color_utils.py
sankalp/utils/table_utils.py
sankalp_deepak-0.1.2.dist-info/METADATA
sankalp_deepak-0.1.2.dist-info/WHEEL
sankalp_deepak-0.1.2.dist-info/entry_points.txt
sankalp_deepak-0.1.2.dist-info/RECORD
